copyxnat/__init__.py
copyxnat/__main__.py
copyxnat/api/__init__.py
copyxnat/api/run_command.py
copyxnat/commands/__init__.py
copyxnat/commands/check_datatypes_command.py
copyxnat/commands/compare_command.py
copyxnat/commands/copy_command.py
copyxnat/commands/export_command.py
copyxnat/commands/find_commands.py
copyxnat/commands/ohif_command.py
copyxnat/commands/rebuild_catalog_command.py
copyxnat/commands/show_command.py
copyxnat/config/__init__.py
copyxnat/config/app_settings.py
copyxnat/config/server_params.py
copyxnat/pyreporter/__init__.py
copyxnat/pyreporter/console.py
copyxnat/pyreporter/console_logger.py
copyxnat/pyreporter/file_logger.py
copyxnat/pyreporter/progress.py
copyxnat/pyreporter/pyreporter.py
copyxnat/ui/__init__.py
copyxnat/ui/command_line.py
copyxnat/utils/__init__.py
copyxnat/utils/error_utils.py
copyxnat/utils/network_utils.py
copyxnat/utils/rsync.py
copyxnat/utils/versioneer_version.py
copyxnat/utils/versioning.py
copyxnat/xnat/__init__.py
copyxnat/xnat/commands.py
copyxnat/xnat/copy_cache.py
copyxnat/xnat/xml_cleaner.py
copyxnat/xnat/xnat_interface.py
copyxnat/xnat/xnat_xml.py
copyxnat/xnat_backend/__init__.py
copyxnat/xnat_backend/lazy_list.py
copyxnat/xnat_backend/pyxnat_server.py
copyxnat/xnat_backend/server_factory.py
copyxnat/xnat_backend/simple_xnat.py
copyxnat/xnat_backend/utis.py
copyxnat/xnat_backend/xnat_rest_client.py
copyxnat/xnat_backend/xnat_session.py
copyxnat-0.9.6.dist-info/LICENSE
copyxnat-0.9.6.dist-info/METADATA
copyxnat-0.9.6.dist-info/WHEEL
copyxnat-0.9.6.dist-info/entry_points.txt
copyxnat-0.9.6.dist-info/top_level.txt
copyxnat-0.9.6.dist-info/RECORD
