Metadata-Version: 2.1
Name: copyxnat
Version: 0.9.6
Summary: CopyXnat is a python utility for copying XNAT projects from one XNAT server to another
Home-page: https://github.com/tomdoel/copyxnat
Author: Tom Doel
License: MIT License
Keywords: medical imaging
Platform: UNKNOWN
Classifier: Development Status :: 3 - Alpha
Classifier: Intended Audience :: Developers
Classifier: Intended Audience :: Healthcare Industry
Classifier: Intended Audience :: Information Technology
Classifier: Intended Audience :: Science/Research
Classifier: Programming Language :: Python
Classifier: Programming Language :: Python :: 2.7
Classifier: Programming Language :: Python :: 3
Classifier: Topic :: Scientific/Engineering :: Information Analysis
Classifier: Topic :: Scientific/Engineering :: Medical Science Apps.
Requires-Python: >=2.7
Requires-Dist: pyxnat (>=1.4)
Requires-Dist: configparser (==4.0.2)
Requires-Dist: urllib3 (>=1.26.3)
Requires-Dist: pydicom (==1.4.2)
Requires-Dist: appdirs (>=1.4.4)
Requires-Dist: lxml (>=4.6.2)
Requires-Dist: xmltodict (>=0.12.0)
Requires-Dist: six (>=1.16.0)
Requires-Dist: enum34 (>=1.1.10)
